mlbtc/__init__.py
mlbtc/__main__.py
mlbtc/coordinates.py
MLB_Trajectory_Calculator-0.1.0.dist-info/LICENSE
MLB_Trajectory_Calculator-0.1.0.dist-info/METADATA
MLB_Trajectory_Calculator-0.1.0.dist-info/WHEEL
MLB_Trajectory_Calculator-0.1.0.dist-info/top_level.txt
MLB_Trajectory_Calculator-0.1.0.dist-info/RECORD
