Metadata-Version: 2.1
Name: MLB-Trajectory-Calculator
Version: 0.1.0
Summary: A Python package for calculating and simulating MLB batted ball trajectories.
Author-email: Jacob Lee <Jacob.J.Lee@outlook.com>
License: MIT License
Project-URL: homepage, https://github.com/JacobLee23/MLB-Trajectory-Calculator
Classifier: Development Status :: 2 - Pre-Alpha
Classifier: License :: OSI Approved :: MIT License
Classifier: Natural Language :: English
Classifier: Operating System :: OS Independent
Classifier: Programming Language :: Python
Classifier: Programming Language :: Python :: 3
Classifier: Programming Language :: Python :: 3.8
Classifier: Programming Language :: Python :: 3.9
Classifier: Programming Language :: Python :: 3.10
Classifier: Programming Language :: Python :: 3.11
Requires-Python: >=3.8
License-File: LICENSE
Requires-Dist: numpy ==1.25.2
